[
  {
    "id": "98688fb2-a4fe-433f-b23c-f5cda2c1a190",
    "establishmentId": 8201,
    "site": "The Marquis of Granby Replenishment Centre",
    "name": "6965",
    "area": 1.89,
    "suitability": [
      "LA",
      "NHP"
    ],
    "holding": [
      "LTH"
    ],
    "restrictions": "Lorem ipsum dolor sit amet"
  },
  {
    "establishmentId": 8201,
    "site": "The Marquis of Granby Replenishment Centre",
    "name": "8",
    "area": 7.06,
    "suitability": [
      "SA",
      "AV",
      "LA"
    ],
    "holding": [
      "STH"
    ],
    "restrictions": "Lorem ipsum dolor sit amet"
  },
  {
    "establishmentId": 8201,
    "site": "Lunar House 3rd floor",
    "name": "4",
    "area": 9.57,
    "suitability": [
      "LA",
      "EQU",
      "DOG"
    ],
    "holding": [
      "LTH",
      "SEP"
    ],
    "restrictions": "Lorem ipsum dolor sit amet"
  },
  {
    "establishmentId": 8201,
    "site": "Metro Point",
    "name": "7584",
    "area": 3.55,
    "suitability": [
      "EQU",
      "NHP",
      "SA"
    ],
    "holding": [
      "STH",
      "NSEP"
    ],
    "restrictions": "Lorem ipsum dolor sit amet"
  },
  {
    "establishmentId": 8201,
    "site": "Lunar House 3rd floor",
    "name": "67",
    "area": 6.59,
    "suitability": [
      "AQ",
      "CAT",
      "AV"
    ],
    "holding": [
      "SEP",
      "STH"
    ],
    "restrictions": "Lorem ipsum dolor sit amet"
  },
  {
    "establishmentId": 8201,
    "site": "Lunar House 3rd floor",
    "name": "94382",
    "area": 6.08,
    "suitability": [
      "EQU",
      "NHP",
      "SA"
    ],
    "holding": [
      "LTH"
    ],
    "restrictions": "Lorem ipsum dolor sit amet"
  },
  {
    "establishmentId": 8201,
    "site": "The Marquis of Granby Replenishment Centre",
    "name": "84",
    "area": 2.06,
    "suitability": [
      "EQU",
      "CAT"
    ],
    "holding": [
      "STH",
      "LTH"
    ],
    "restrictions": "Lorem ipsum dolor sit amet"
  },
  {
    "id": "de08df0e-c178-4c53-9eea-7132eee24b4d",
    "establishmentId": 8201,
    "site": "2 Marsham Street",
    "name": "377",
    "area": 2.27,
    "suitability": [
      "NHP",
      "CAT",
      "DOG"
    ],
    "holding": [
      "SEP"
    ],
    "restrictions": "Lorem ipsum dolor sit amet",
    "roles": [
      "232b302b-136b-4452-ba1c-1e5a867212a1",
      "6cb73cb3-3960-4d71-b4ca-15697bd35b37",
      "7a5d191c-ed47-41fe-8aed-0d33efe66a02"
    ]
  },
  {
    "establishmentId": 8201,
    "site": "Regus Building",
    "name": "52",
    "area": 8.13,
    "suitability": [
      "AV"
    ],
    "holding": [
      "STH",
      "SEP"
    ],
    "restrictions": "Lorem ipsum dolor sit amet"
  },
  {
    "establishmentId": 8201,
    "site": "Regus Building",
    "name": "14",
    "area": null,
    "suitability": [
      "DOG",
      "EQU"
    ],
    "holding": [
      "STH",
      "NOH"
    ],
    "restrictions": "Lorem ipsum dolor sit amet"
  },
  {
    "establishmentId": 8201,
    "site": "Vulcan House",
    "name": "23",
    "area": 8.89,
    "suitability": [
      "SA"
    ],
    "holding": [
      "SEP",
      "LTH"
    ],
    "restrictions": "Lorem ipsum dolor sit amet"
  },
  {
    "establishmentId": 8201,
    "site": "Lunar House 3rd floor",
    "name": "83",
    "area": 7.09,
    "suitability": [
      "LA",
      "EQU",
      "DOG"
    ],
    "holding": [
      "NOH"
    ],
    "restrictions": "Lorem ipsum dolor sit amet"
  },
  {
    "establishmentId": 8201,
    "site": "Regus Building",
    "name": "1",
    "area": null,
    "suitability": [
      "NHP"
    ],
    "holding": [
      "NOH"
    ],
    "restrictions": "Lorem ipsum dolor sit amet"
  },
  {
    "establishmentId": 8201,
    "site": "Lunar House 2nd floor",
    "name": "0",
    "area": 7.34,
    "suitability": [
      "AQ"
    ],
    "holding": [
      "NSEP",
      "LTH"
    ],
    "restrictions": "Lorem ipsum dolor sit amet"
  },
  {
    "establishmentId": 8201,
    "site": "Regus Building",
    "name": "530",
    "area": null,
    "suitability": [
      "DOG",
      "NHP",
      "SA"
    ],
    "holding": [
      "NOH",
      "LTH"
    ],
    "restrictions": "Lorem ipsum dolor sit amet"
  },
  {
    "establishmentId": 8201,
    "site": "Lunar House 2nd floor",
    "name": "13143",
    "area": null,
    "suitability": [
      "DOG",
      "SA"
    ],
    "holding": [
      "SEP"
    ],
    "restrictions": "Lorem ipsum dolor sit amet"
  },
  {
    "establishmentId": 8201,
    "site": "The Marquis of Granby Replenishment Centre",
    "name": "65544",
    "area": 6.47,
    "suitability": [
      "LA",
      "SA"
    ],
    "holding": [
      "STH"
    ],
    "restrictions": "Lorem ipsum dolor sit amet"
  },
  {
    "establishmentId": 8201,
    "site": "The Marquis of Granby Replenishment Centre",
    "name": "1305",
    "area": 4.34,
    "suitability": [
      "DOG"
    ],
    "holding": [
      "SEP",
      "LTH"
    ],
    "restrictions": "Lorem ipsum dolor sit amet"
  },
  {
    "establishmentId": 8201,
    "site": "Vulcan House",
    "name": "505",
    "area": 9.69,
    "suitability": [
      "SA",
      "EQU"
    ],
    "holding": [
      "STH",
      "SEP"
    ]
  },
  {
    "establishmentId": 8201,
    "site": "Lunar House 4th floor",
    "name": "26",
    "area": 8.38,
    "suitability": [
      "NHP"
    ],
    "holding": [
      "NOH",
      "LTH"
    ]
  },
  {
    "establishmentId": 8201,
    "site": "Lunar House 2nd floor",
    "name": "302",
    "area": 2.46,
    "suitability": [
      "LA",
      "AQ",
      "AV"
    ],
    "holding": [
      "STH",
      "NOH"
    ]
  },
  {
    "establishmentId": 8201,
    "site": "Lunar House 1st floor",
    "name": "3304",
    "area": 9.21,
    "suitability": [
      "AQ",
      "EQU"
    ],
    "holding": [
      "NSEP"
    ]
  },
  {
    "establishmentId": 8201,
    "site": "The Marquis of Granby Replenishment Centre",
    "name": "06329",
    "area": null,
    "suitability": [
      "SA"
    ],
    "holding": [
      "NSEP",
      "LTH"
    ]
  },
  {
    "establishmentId": 8201,
    "site": "Apollo House",
    "name": "040",
    "area": 4.1,
    "suitability": [
      "CAT",
      "DOG"
    ],
    "holding": [
      "SEP",
      "STH"
    ]
  },
  {
    "establishmentId": 8201,
    "site": "Vulcan House",
    "name": "8209",
    "area": null,
    "suitability": [
      "AV",
      "EQU"
    ],
    "holding": [
      "STH"
    ]
  },
  {
    "establishmentId": 8201,
    "site": "Metro Point",
    "name": "6911",
    "area": 2.5,
    "suitability": [
      "DOG"
    ],
    "holding": [
      "LTH",
      "SEP"
    ]
  },
  {
    "establishmentId": 8201,
    "site": "Lunar House 3rd floor",
    "name": "6121",
    "area": null,
    "suitability": [
      "LA",
      "DOG",
      "NHP"
    ],
    "holding": [
      "NSEP"
    ]
  },
  {
    "establishmentId": 8201,
    "site": "The Marquis of Granby Replenishment Centre",
    "name": "431",
    "area": 4.39,
    "suitability": [
      "EQU",
      "LA"
    ],
    "holding": [
      "NOH",
      "SEP"
    ]
  },
  {
    "establishmentId": 8201,
    "site": "Lunar House 4th floor",
    "name": "21",
    "area": 3.36,
    "suitability": [
      "AQ",
      "SA",
      "CAT"
    ],
    "holding": [
      "NOH"
    ]
  },
  {
    "establishmentId": 8201,
    "site": "Lunar House 5th floor",
    "name": "45",
    "area": null,
    "suitability": [
      "AQ",
      "DOG"
    ],
    "holding": [
      "LTH"
    ]
  },
  {
    "establishmentId": 8201,
    "site": "Lunar House 1st floor",
    "name": "0008",
    "area": null,
    "suitability": [
      "NHP"
    ],
    "holding": [
      "LTH",
      "NOH"
    ]
  },
  {
    "establishmentId": 8201,
    "site": "Lunar House 5th floor",
    "name": "179",
    "area": 6.41,
    "suitability": [
      "AV"
    ],
    "holding": [
      "NOH"
    ]
  },
  {
    "establishmentId": 8201,
    "site": "Lunar House 4th floor",
    "name": "67",
    "area": 7.91,
    "suitability": [
      "NHP"
    ],
    "holding": [
      "STH"
    ]
  },
  {
    "establishmentId": 8201,
    "site": "Lunar House 5th floor",
    "name": "3",
    "area": 5.93,
    "suitability": [
      "EQU"
    ],
    "holding": [
      "NOH",
      "SEP"
    ]
  },
  {
    "establishmentId": 8201,
    "site": "Lunar House 3rd floor",
    "name": "10137",
    "area": 1.62,
    "suitability": [
      "LA",
      "AQ"
    ],
    "holding": [
      "SEP",
      "NSEP"
    ]
  },
  {
    "establishmentId": 8201,
    "site": "Lunar House 1st floor",
    "name": "116",
    "area": 6.93,
    "suitability": [
      "EQU"
    ],
    "holding": [
      "STH"
    ]
  },
  {
    "establishmentId": 8201,
    "site": "Lunar House 5th floor",
    "name": "7284",
    "area": 5.31,
    "suitability": [
      "SA",
      "AQ"
    ],
    "holding": [
      "STH"
    ]
  },
  {
    "establishmentId": 8201,
    "site": "Lunar House 4th floor",
    "name": "0",
    "area": 2.74,
    "suitability": [
      "EQU",
      "SA"
    ],
    "holding": [
      "SEP",
      "LTH"
    ]
  },
  {
    "establishmentId": 8201,
    "site": "Lunar House 2nd floor",
    "name": "490",
    "area": null,
    "suitability": [
      "AV",
      "LA",
      "DOG"
    ],
    "holding": [
      "NOH"
    ]
  },
  {
    "establishmentId": 8201,
    "site": "Lunar House 1st floor",
    "name": "63619",
    "area": 3.34,
    "suitability": [
      "AV",
      "EQU"
    ],
    "holding": [
      "LTH"
    ]
  },
  {
    "establishmentId": 8201,
    "site": "The Marquis of Granby Replenishment Centre",
    "name": "756",
    "area": 6.32,
    "suitability": [
      "AV",
      "EQU",
      "LA"
    ],
    "holding": [
      "NOH",
      "STH"
    ]
  },
  {
    "establishmentId": 8201,
    "site": "Metro Point",
    "name": "78",
    "area": null,
    "suitability": [
      "LA",
      "DOG",
      "NHP"
    ],
    "holding": [
      "NSEP"
    ]
  },
  {
    "establishmentId": 8201,
    "site": "Lunar House 3rd floor",
    "name": "723",
    "area": 5.92,
    "suitability": [
      "CAT"
    ],
    "holding": [
      "SEP"
    ]
  },
  {
    "establishmentId": 8201,
    "site": "Metro Point",
    "name": "26",
    "area": null,
    "suitability": [
      "CAT",
      "AQ"
    ],
    "holding": [
      "NOH",
      "LTH"
    ]
  },
  {
    "establishmentId": 8201,
    "site": "Apollo House",
    "name": "049",
    "area": 8.3,
    "suitability": [
      "CAT",
      "LA",
      "DOG"
    ],
    "holding": [
      "NOH"
    ]
  },
  {
    "establishmentId": 8201,
    "site": "Lunar House 3rd floor",
    "name": "297",
    "area": 1.38,
    "suitability": [
      "DOG"
    ],
    "holding": [
      "NOH",
      "LTH"
    ]
  },
  {
    "establishmentId": 8201,
    "site": "Lunar House 5th floor",
    "name": "40",
    "area": 3.29,
    "suitability": [
      "EQU",
      "CAT",
      "AV"
    ],
    "holding": [
      "LTH",
      "NOH"
    ]
  },
  {
    "establishmentId": 8201,
    "site": "Lunar House 1st floor",
    "name": "74",
    "area": null,
    "suitability": [
      "DOG"
    ],
    "holding": [
      "STH"
    ]
  },
  {
    "establishmentId": 8201,
    "site": "Lunar House 1st floor",
    "name": "49",
    "area": 1.01,
    "suitability": [
      "DOG",
      "AV",
      "CAT"
    ],
    "holding": [
      "NOH",
      "LTH"
    ]
  },
  {
    "establishmentId": 8201,
    "site": "Lunar House 5th floor",
    "name": "33",
    "area": 3.67,
    "suitability": [
      "NHP"
    ],
    "holding": [
      "SEP",
      "NOH"
    ]
  },
  {
    "id": "30041acc-28fb-429e-b2c7-68ce07d88172",
    "establishmentId": 8201,
    "site": "2 Marsham Street",
    "name": "919",
    "area": null,
    "suitability": [
      "EQU",
      "LA"
    ],
    "holding": [
      "NSEP",
      "LTH"
    ],
    "roles": ["232b302b-136b-4452-ba1c-1e5a867212a1"]
  },
  {
    "establishmentId": 8201,
    "site": "The Marquis of Granby Replenishment Centre",
    "name": "942",
    "area": 8.91,
    "suitability": [
      "CAT"
    ],
    "holding": [
      "SEP",
      "NOH"
    ]
  },
  {
    "establishmentId": 8201,
    "site": "Lunar House 5th floor",
    "name": "17236",
    "area": 6.26,
    "suitability": [
      "SA"
    ],
    "holding": [
      "SEP",
      "NSEP"
    ]
  },
  {
    "establishmentId": 8201,
    "site": "Apollo House",
    "name": "0661",
    "area": null,
    "suitability": [
      "CAT"
    ],
    "holding": [
      "NSEP",
      "STH"
    ]
  },
  {
    "establishmentId": 8201,
    "site": "Apollo House",
    "name": "07",
    "area": 1.62,
    "suitability": [
      "AQ"
    ],
    "holding": [
      "STH",
      "LTH"
    ]
  },
  {
    "establishmentId": 8201,
    "site": "Lunar House 3rd floor",
    "name": "9",
    "area": 7.3,
    "suitability": [
      "LA",
      "NHP"
    ],
    "holding": [
      "SEP",
      "NSEP"
    ]
  },
  {
    "establishmentId": 8201,
    "site": "Regus Building",
    "name": "1",
    "area": null,
    "suitability": [
      "CAT",
      "EQU",
      "NHP"
    ],
    "holding": [
      "STH",
      "NOH"
    ]
  },
  {
    "establishmentId": 8201,
    "site": "Metro Point",
    "name": "5716",
    "area": 7.81,
    "suitability": [
      "DOG"
    ],
    "holding": [
      "NOH",
      "NSEP"
    ]
  },
  {
    "establishmentId": 8201,
    "site": "Lunar House 5th floor",
    "name": "674",
    "area": 2.13,
    "suitability": [
      "LA"
    ],
    "holding": [
      "SEP"
    ]
  },
  {
    "establishmentId": 8201,
    "site": "Lunar House 3rd floor",
    "name": "727",
    "area": 6.18,
    "suitability": [
      "AV",
      "NHP"
    ],
    "holding": [
      "SEP"
    ]
  },
  {
    "establishmentId": 8201,
    "site": "Regus Building",
    "name": "27",
    "area": null,
    "suitability": [
      "DOG"
    ],
    "holding": [
      "NOH"
    ]
  },
  {
    "establishmentId": 8201,
    "site": "Lunar House 1st floor",
    "name": "66401",
    "area": 5.65,
    "suitability": [
      "EQU",
      "NHP",
      "DOG"
    ],
    "holding": [
      "NOH",
      "NSEP"
    ]
  },
  {
    "establishmentId": 8201,
    "site": "Lunar House 5th floor",
    "name": "192",
    "area": null,
    "suitability": [
      "SA"
    ],
    "holding": [
      "NSEP"
    ]
  },
  {
    "establishmentId": 8201,
    "site": "Lunar House 1st floor",
    "name": "807",
    "area": 2.63,
    "suitability": [
      "CAT",
      "LA",
      "AQ"
    ],
    "holding": [
      "LTH"
    ]
  },
  {
    "establishmentId": 8201,
    "site": "Lunar House 5th floor",
    "name": "957",
    "area": 1.47,
    "suitability": [
      "NHP",
      "EQU",
      "SA"
    ],
    "holding": [
      "LTH",
      "NOH"
    ]
  },
  {
    "establishmentId": 8201,
    "site": "Regus Building",
    "name": "3",
    "area": 5.12,
    "suitability": [
      "CAT"
    ],
    "holding": [
      "LTH"
    ]
  },
  {
    "establishmentId": 8201,
    "site": "Vulcan House",
    "name": "581",
    "area": 1.41,
    "suitability": [
      "AQ",
      "EQU",
      "DOG"
    ],
    "holding": [
      "STH",
      "LTH"
    ]
  },
  {
    "establishmentId": 8201,
    "site": "Vulcan House",
    "name": "21236",
    "area": 5.2,
    "suitability": [
      "SA"
    ],
    "holding": [
      "SEP",
      "LTH"
    ]
  },
  {
    "id": "bf003bd2-27bc-4a32-92fe-87dd3d595763",
    "establishmentId": 8201,
    "site": "2 Marsham Street",
    "name": "61715",
    "area": 9.25,
    "suitability": [
      "AQ"
    ],
    "holding": [
      "NSEP",
      "NOH"
    ],
    "roles": ["232b302b-136b-4452-ba1c-1e5a867212a1"]
  },
  {
    "establishmentId": 8201,
    "site": "Lunar House 2nd floor",
    "name": "9",
    "area": null,
    "suitability": [
      "AQ",
      "DOG"
    ],
    "holding": [
      "STH"
    ]
  },
  {
    "establishmentId": 8201,
    "site": "Regus Building",
    "name": "57744",
    "area": 6.62,
    "suitability": [
      "EQU",
      "AV",
      "DOG"
    ],
    "holding": [
      "STH",
      "NOH"
    ]
  },
  {
    "establishmentId": 8201,
    "site": "The Marquis of Granby Replenishment Centre",
    "name": "28",
    "area": 7.57,
    "suitability": [
      "LA"
    ],
    "holding": [
      "NSEP",
      "NOH"
    ]
  },
  {
    "establishmentId": 8201,
    "site": "Regus Building",
    "name": "4469",
    "area": 3.93,
    "suitability": [
      "AV",
      "CAT",
      "DOG"
    ],
    "holding": [
      "LTH"
    ]
  },
  {
    "establishmentId": 8201,
    "site": "Apollo House",
    "name": "9541",
    "area": null,
    "suitability": [
      "CAT",
      "AQ"
    ],
    "holding": [
      "STH",
      "NSEP"
    ]
  },
  {
    "establishmentId": 8201,
    "site": "Metro Point",
    "name": "226",
    "area": 1.53,
    "suitability": [
      "AV"
    ],
    "holding": [
      "NSEP",
      "STH"
    ]
  },
  {
    "establishmentId": 8201,
    "site": "Regus Building",
    "name": "96",
    "area": 1.64,
    "suitability": [
      "LA",
      "NHP"
    ],
    "holding": [
      "NOH",
      "STH"
    ]
  },
  {
    "establishmentId": 8201,
    "site": "Lunar House 2nd floor",
    "name": "1",
    "area": 7.15,
    "suitability": [
      "EQU",
      "DOG"
    ],
    "holding": [
      "LTH",
      "NOH"
    ]
  },
  {
    "establishmentId": 8201,
    "site": "Lunar House 5th floor",
    "name": "135",
    "area": 7.54,
    "suitability": [
      "SA",
      "EQU",
      "NHP"
    ],
    "holding": [
      "LTH",
      "NOH"
    ]
  },
  {
    "establishmentId": 8201,
    "site": "Apollo House",
    "name": "87",
    "area": 4.48,
    "suitability": [
      "AV",
      "NHP"
    ],
    "holding": [
      "NSEP"
    ]
  },
  {
    "establishmentId": 8201,
    "site": "Lunar House 3rd floor",
    "name": "17772",
    "area": 4.7,
    "suitability": [
      "NHP"
    ],
    "holding": [
      "STH"
    ]
  },
  {
    "establishmentId": 8201,
    "site": "Lunar House 1st floor",
    "name": "33386",
    "area": 9.66,
    "suitability": [
      "NHP",
      "AV",
      "LA"
    ],
    "holding": [
      "LTH"
    ]
  },
  {
    "establishmentId": 8201,
    "site": "Lunar House 3rd floor",
    "name": "01554",
    "area": 1.83,
    "suitability": [
      "SA"
    ],
    "holding": [
      "SEP"
    ]
  },
  {
    "establishmentId": 8201,
    "site": "The Marquis of Granby Replenishment Centre",
    "name": "847",
    "area": null,
    "suitability": [
      "SA",
      "LA"
    ],
    "holding": [
      "SEP",
      "LTH"
    ]
  },
  {
    "id": "f366959a-1e3d-4cca-8611-0b9a44d15e10",
    "establishmentId": 8201,
    "site": "2 Marsham Street",
    "name": "1603",
    "area": 8.17,
    "suitability": [
      "CAT",
      "AQ"
    ],
    "holding": [
      "LTH",
      "NOH"
    ],
    "roles": ["232b302b-136b-4452-ba1c-1e5a867212a1"]
  },
  {
    "establishmentId": 8201,
    "site": "Metro Point",
    "name": "13",
    "area": 5.2,
    "suitability": [
      "LA",
      "CAT",
      "DOG"
    ],
    "holding": [
      "LTH"
    ]
  },
  {
    "establishmentId": 8201,
    "site": "Vulcan House",
    "name": "6",
    "area": 8.69,
    "suitability": [
      "CAT"
    ],
    "holding": [
      "STH"
    ]
  },
  {
    "establishmentId": 8201,
    "site": "Vulcan House",
    "name": "865",
    "area": 2.53,
    "suitability": [
      "LA",
      "AV"
    ],
    "holding": [
      "NSEP"
    ]
  },
  {
    "establishmentId": 8201,
    "site": "The Marquis of Granby Replenishment Centre",
    "name": "5700",
    "area": null,
    "suitability": [
      "EQU",
      "AV"
    ],
    "holding": [
      "STH"
    ]
  },
  {
    "establishmentId": 8201,
    "site": "The Marquis of Granby Replenishment Centre",
    "name": "2",
    "area": 5.14,
    "suitability": [
      "SA",
      "AV"
    ],
    "holding": [
      "STH"
    ]
  },
  {
    "establishmentId": 8201,
    "site": "Lunar House 3rd floor",
    "name": "81457",
    "area": null,
    "suitability": [
      "AQ"
    ],
    "holding": [
      "LTH"
    ]
  },
  {
    "establishmentId": 8201,
    "site": "Lunar House 4th floor",
    "name": "3312",
    "area": 1.99,
    "suitability": [
      "AQ",
      "EQU"
    ],
    "holding": [
      "LTH"
    ]
  },
  {
    "id": "ddf938c8-4b6c-485d-9699-75c0a43694bf",
    "establishmentId": 8201,
    "site": "3 Marsham Street",
    "name": "58816",
    "area": null,
    "suitability": [
      "CAT"
    ],
    "holding": [
      "LTH",
      "SEP"
    ],
    "roles": []
  },
  {
    "establishmentId": 8201,
    "site": "Apollo House",
    "name": "9706",
    "area": 7.13,
    "suitability": [
      "EQU",
      "AQ"
    ],
    "holding": [
      "NOH",
      "LTH"
    ]
  },
  {
    "establishmentId": 8201,
    "site": "Apollo House",
    "name": "05411",
    "area": 8.82,
    "suitability": [
      "AV"
    ],
    "holding": [
      "LTH",
      "SEP"
    ]
  },
  {
    "establishmentId": 8201,
    "site": "Metro Point",
    "name": "44",
    "area": null,
    "suitability": [
      "AV",
      "AQ",
      "EQU"
    ],
    "holding": [
      "LTH",
      "NSEP"
    ]
  },
  {
    "establishmentId": 8201,
    "site": "Lunar House 5th floor",
    "name": "642",
    "area": 3.11,
    "suitability": [
      "DOG"
    ],
    "holding": [
      "NSEP"
    ]
  },
  {
    "establishmentId": 8201,
    "site": "Lunar House 5th floor",
    "name": "40",
    "area": 7.8,
    "suitability": [
      "EQU",
      "NHP"
    ],
    "holding": [
      "SEP",
      "NSEP"
    ]
  },
  {
    "establishmentId": 8201,
    "site": "Lunar House 2nd floor",
    "name": "0",
    "area": 5.76,
    "suitability": [
      "AV",
      "EQU"
    ],
    "holding": [
      "SEP"
    ]
  },
  {
    "establishmentId": 8201,
    "site": "Lunar House 1st floor",
    "name": "51759",
    "area": null,
    "suitability": [
      "DOG"
    ],
    "holding": [
      "LTH"
    ]
  },
  {
    "establishmentId": 8201,
    "site": "The Marquis of Granby Replenishment Centre",
    "name": "010",
    "area": null,
    "suitability": [
      "AQ",
      "EQU"
    ],
    "holding": [
      "NOH"
    ]
  },
  {
    "id": "b0a1563c-3f94-4d26-8711-9db266b588b5",
    "establishmentId": 8202,
    "site": "Lunar house",
    "name": "111",
    "area": null,
    "suitability": [
      "AQ",
      "EQU"
    ],
    "holding": [
      "NOH"
    ]
  },
  {
    "id": "e5ec422d-dca3-4192-b2bd-bff5f5ac8288",
    "establishmentId": 8202,
    "site": "Marvell HQ",
    "name": "Cattery",
    "area": "Top Floor",
    "suitability": ["CAT"],
    "holding": ["LTH"]
  },
  {
    "establishmentId": 8201,
    "site": "Public edit place tests",
    "area": null,
    "name": "Default"
  },
  {
    "id": "e5f11cfd-7b75-4b7b-9c63-3216feb6e380",
    "establishmentId": 8201,
    "site": "Public edit place tests",
    "area": null,
    "name": "No NACWO",
    "roles": []
  },
  {
    "establishmentId": 8201,
    "site": "Public remove place tests",
    "area": null,
    "name": "Default"
  },
  {
    "establishmentId": 8201,
    "site": "Internal edit place tests",
    "area": null,
    "name": "Default"
  },
  {
    "establishmentId": 8201,
    "site": "Internal restrictions tests",
    "area": null,
    "name": "Default"
  },
  {
    "establishmentId": 30001,
    "site": "Bravo",
    "area": "Bravo",
    "name": "Bravo"
  },
  {
    "establishmentId": 30001,
    "site": "Bravo",
    "area": "Alfa",
    "name": "Bravo"
  },
  {
    "establishmentId": 30001,
    "site": "Charlie",
    "area": "Alfa",
    "name": "Alfa"
  },
  {
    "establishmentId": 30001,
    "site": "Delta",
    "area": null,
    "name": "1N107",
    "restrictions": "Lorem ipsum dolor sit amet"
  },
  {
    "establishmentId": 30001,
    "site": "Delta",
    "area": null,
    "name": "1N109",
    "restrictions": "Lorem ipsum dolor sit amet"
  },
  {
    "establishmentId": 30001,
    "site": "Delta",
    "area": "",
    "name": "1N065",
    "restrictions": "Lorem ipsum dolor sit amet"
  },
  {
    "establishmentId": 30001,
    "site": "Delta",
    "area": null,
    "name": "1N115",
    "restrictions": "Lorem ipsum dolor sit amet"
  },
  {
    "establishmentId": 30001,
    "site": "Delta",
    "area": "",
    "name": "1N390",
    "restrictions": "Lorem ipsum dolor sit amet"
  },
  {
    "establishmentId": 30001,
    "site": "Bravo",
    "area": "Alfa",
    "name": "Alfa"
  },
  {
    "establishmentId": 30001,
    "site": "Alfa",
    "area": "Alfa",
    "name": "Alfa"
  },
  {
    "establishmentId": 30001,
    "site": "Alfa",
    "area": "Charlie",
    "name": "Alfa"
  },
  {
    "establishmentId": 30001,
    "site": "Alfa",
    "area": "Bravo",
    "name": "Charlie"
  },
  {
    "establishmentId": 30001,
    "site": "Alfa",
    "area": "Bravo",
    "name": "Alfa"
  },
  {
    "establishmentId": 30001,
    "site": "Alfa",
    "area": "Alfa",
    "name": "Bravo"
  },
  {
    "id": "98688fb2-a4fe-433f-b23c-f5cda2c1a191",
    "establishmentId": 40001,
    "site": "Test site",
    "name": "101",
    "area": 1.89,
    "suitability": [
      "LA",
      "NHP"
    ],
    "holding": [
      "LTH"
    ],
    "restrictions": "Lorem ipsum dolor sit amet"
  }
]
